{"instagram":{"followers_count":106,"username":"blendup.art","profile_picture_url":"https://scontent-fra3-1.xx.fbcdn.net/v/t51.2885-15/36466265_250880655717033_3149851795669385216_n.jpg?_nc_cat=105&ccb=1-7&_nc_sid=7d201b&_nc_ohc=w8kg-lFGRQgQ7kNvwFOY6Vn&_nc_oc=AdmezFI_UHizIVZeYizhiKSRs-fe7QBudailhJT3RAwed8OJ3rHp8lMCXZ9y4f9z8N8&_nc_zt=23&_nc_ht=scontent-fra3-1.xx&edm=AL-3X8kEAAAA&oh=00_AfGNsWZcGbdNXYjqLtx7oT2ggrJGI22ZCVT6C42fPArBnQ&oe=680CAAD2","reach":7.2,"followers_count_friendly":"106","reach_friendly":"7.2"},"google_analytics":{"total_pageviews":20995,"total_users":17498,"total_pageviews_friendly":"21k","total_users_friendly":"17.5k"},"date":"2025-04-21"}