{"instagram":{"followers_count":12862,"username":"mediajunkbox","profile_picture_url":"https://scontent-fra5-2.xx.fbcdn.net/v/t51.82787-15/562878988_18069321668201074_1212820066486730347_n.jpg?_nc_cat=109&ccb=1-7&_nc_sid=7d201b&_nc_ohc=Q4xZ0FMTYSsQ7kNvwGGt7NX&_nc_oc=AdmmPvqaJeKS84VEXSF4QatHFmYTRxYgTl3WwtId0UT9lUa4miZKgeFY5cFPH1SuX1g&_nc_zt=23&_nc_ht=scontent-fra5-2.xx&edm=AL-3X8kEAAAA&_nc_gid=x1IMoy6ClhOsfXw2O9PEhg&oh=00_AfjRZ1LliLukqrRt3xE2ad-D4RRF3rP3d6o2DycKVDayTA&oe=6911B43C","reach":147427.2,"followers_count_friendly":"12.9k","reach_friendly":"147.4k"},"google_analytics":{"total_pageviews":21463,"total_users":18913,"total_pageviews_friendly":"21.5k","total_users_friendly":"19k"},"date":"2025-11-06"}