{"instagram":{"followers_count":12742,"username":"metaljunkbox","profile_picture_url":"https://scontent-fra5-1.xx.fbcdn.net/v/t51.2885-15/473554507_1097976898740460_5284942109177432973_n.jpg?_nc_cat=110&ccb=1-7&_nc_sid=7d201b&_nc_ohc=HIZIvfUQrK8Q7kNvwF1qlRd&_nc_oc=AdlqHA1Jc9YX6hf1IWluk4aqhDzKIqvcmQ90kOdJ3nL4XVHyQ_4n3oNIBgREu-VT6Zk&_nc_zt=23&_nc_ht=scontent-fra5-1.xx&edm=AL-3X8kEAAAA&oh=00_AfWYdYsY9AVs5MsAv8I83NCCysCCTEEzZLecE4Btj6zugQ&oe=68B7FFB3","reach":128030.4,"followers_count_friendly":"12.7k","reach_friendly":"128.0k"},"google_analytics":{"total_pageviews":15358,"total_users":7952,"total_pageviews_friendly":"15.4k","total_users_friendly":"8k"},"date":"2025-08-29"}