{"instagram":{"followers_count":12550,"username":"metaljunkbox","profile_picture_url":"https://scontent-fra5-1.xx.fbcdn.net/v/t51.2885-15/473554507_1097976898740460_5284942109177432973_n.jpg?_nc_cat=110&ccb=1-7&_nc_sid=7d201b&_nc_ohc=goDUvLOKJLUQ7kNvwF4tNml&_nc_oc=Adk1HsTJSLdarCdl8Rlrv6PejHNTOny2rVCA84JEDG561laXvuQ0m7bDZ8SmASfO634&_nc_zt=23&_nc_ht=scontent-fra5-1.xx&edm=AL-3X8kEAAAA&oh=00_AfO5sA3QO5eEHpgTXXzeMYwZ-kA-fod-daq0KLAx6J4Lpg&oe=685D0833","reach":138938.4,"followers_count_friendly":"12.6k","reach_friendly":"138.9k"},"google_analytics":{"total_pageviews":13588,"total_users":9452,"total_pageviews_friendly":"13.6k","total_users_friendly":"9.5k"},"date":"2025-06-21"}