{"instagram":{"followers_count":13080,"username":"mediajunkbox","profile_picture_url":"https://scontent-fra5-2.xx.fbcdn.net/v/t51.82787-15/562878988_18069321668201074_1212820066486730347_n.jpg?_nc_cat=109&ccb=1-7&_nc_sid=7d201b&_nc_ohc=9bFRFd4ZLZQQ7kNvwH7ygki&_nc_oc=AdphFVfuz-3x9t16JLY5sYM9ilSKC4SwRJataSYInoSwqJi7WtQ7wHJsyFcdHUCXcOk&_nc_zt=23&_nc_ht=scontent-fra5-2.xx&edm=AL-3X8kEAAAA&_nc_gid=YgnMIy_nyTvvaxRUUIH2qA&oh=00_Af8YS2zl_9Pv04hhAbuk5Wyz-WML410iMspbaF4GSE-dMQ&oe=6A350FBC","reach":73065.6,"followers_count_friendly":"13.1k","reach_friendly":"73.1k"},"google_analytics":{"total_pageviews":6914,"total_users":4045,"total_pageviews_friendly":"7k","total_users_friendly":"4.1k"},"date":"2026-06-14"}